{
  "questions": [
    {
      "level": "surface",
      "question": "What are the two types of adders discussed?",
      "model_answer": "Award 1 mark for any two of the following: Half adders, Full adders.",
      "student_answer": null,
      "score": null,
      "explanation": null,
      "source_pages": [
        1,
        2,
        3
      ],
      "section": "Half Adders"
    },
    {
      "level": "surface",
      "question": "What are the two outputs of a half adder?",
      "model_answer": "Award 1 mark for any two of the following: Sum (S), Carried bit (C).",
      "student_answer": null,
      "score": null,
      "explanation": null,
      "source_pages": [
        1,
        2,
        3
      ],
      "section": "Half Adders"
    },
    {
      "level": "surface",
      "question": "What is the term for the bits being added together by an adder?",
      "model_answer": "Award 1 mark for 'addends'.",
      "student_answer": null,
      "score": null,
      "explanation": null,
      "source_pages": [
        1,
        2,
        3
      ],
      "section": "COMPUTER ARCHITECTURE ADDER CIRCUIT"
    },
    {
      "level": "conceptual",
      "question": "Explain how the sum bit is generated in a half adder.",
      "model_answer": "Award 1 mark for explaining that the sum bit is the modulo-2 sum of the addends, and can be generated by an XOR gate. Accept any description referencing the addends being different.",
      "student_answer": null,
      "score": null,
      "explanation": null,
      "source_pages": [
        1,
        2,
        3
      ],
      "section": "Half Adders"
    },
    {
      "level": "conceptual",
      "question": "Describe the limitation of a half adder in adding multiple-bit numbers.",
      "model_answer": "Award 1 mark for explaining that half adders cannot handle a carry-in signal.",
      "student_answer": null,
      "score": null,
      "explanation": null,
      "source_pages": [
        1,
        2,
        3
      ],
      "section": "Half Adders"
    },
    {
      "level": "conceptual",
      "question": "What additional input does a full adder have compared to a half adder?",
      "model_answer": "Award 1 mark for stating that a full adder has a carry-in input (Cin).",
      "student_answer": null,
      "score": null,
      "explanation": null,
      "source_pages": [
        2,
        3
      ],
      "section": "Full Adders"
    },
    {
      "level": "conceptual",
      "question": "How is the carried bit (carry-out) generated in a half adder?",
      "model_answer": "Award 1 mark for explaining that the carried bit is generated when both addends are 1, and can be produced by an AND gate.",
      "student_answer": null,
      "score": null,
      "explanation": null,
      "source_pages": [
        1,
        2,
        3
      ],
      "section": "Half Adders"
    },
    {
      "level": "deep",
      "question": "Given the inability of a half adder to accept a carry-in, describe a scenario where a full adder would be essential for performing an addition.",
      "model_answer": "Award 1 mark for describing a scenario involving adding binary numbers with more than one bit, where a carry from a less significant bit needs to be incorporated into the addition of the next more significant bit. Accept any example demonstrating multi-bit addition.",
      "student_answer": null,
      "score": null,
      "explanation": null,
      "source_pages": [
        1,
        2,
        3
      ],
      "section": "Half Adders"
    },
    {
      "level": "deep",
      "question": "If a circuit designer needs to add two 4-bit binary numbers, how many half adders and full adders would be required, and how would they be connected?",
      "model_answer": "Award 1 mark for stating that one full adder is needed for the least significant bit, followed by three more full adders for the remaining bits. Accept any description of a ripple-carry adder structure where the carry-out of one stage becomes the carry-in of the next, and the initial carry-in is typically 0.",
      "student_answer": null,
      "score": null,
      "explanation": null,
      "source_pages": [
        1,
        2,
        3
      ],
      "section": "Half Adders"
    },
    {
      "level": "deep",
      "question": "Construct the logic expression for the sum (S) and carry-out (Cout) of a full adder, given inputs A, B, and Cin.",
      "model_answer": "Award 1 mark for correctly stating the logic expressions: S = A XOR B XOR Cin, Cout = (A AND B) OR (Cin AND (A XOR B)).",
      "student_answer": null,
      "score": null,
      "explanation": null,
      "source_pages": [
        1,
        2,
        3
      ],
      "section": "Half Adders"
    }
  ]
}